.DS_Store
boxv2/__init__.py
boxv2/auth.py
boxv2/exceptions.py
boxv2/request.py
boxv2/session.py
boxv2/session_bk.py
boxv2/upload.py
boxv2-0.1.3.5.dist-info/DESCRIPTION.rst
boxv2-0.1.3.5.dist-info/METADATA
boxv2-0.1.3.5.dist-info/metadata.json
boxv2-0.1.3.5.dist-info/RECORD
boxv2-0.1.3.5.dist-info/top_level.txt
boxv2-0.1.3.5.dist-info/WHEEL
