Metadata-Version: 2.0
Name: boxv2
Version: 0.1.3.5
Summary: Box Python SDK for v2 of the Box.com API.
Home-page: http://github.com/Octonius/boxv2/
Author: octonius
Author-email: dev@octonius.com
License: MIT
Platform: UNKNOWN
Classifier: Development Status :: 5 - Production/Stable
Classifier: Intended Audience :: Developers
Classifier: Natural Language :: English
Classifier: License :: OSI Approved :: MIT License
Classifier: Operating System :: OS Independent
Classifier: Programming Language :: Python
Classifier: Programming Language :: Python :: 2.7
Classifier: Topic :: Software Development :: Libraries :: Python Modules
Requires-Dist: requests
